{"788724":{"Ngày sinh và tuổi":[{"{{Ngày sinh và tuổi|df":"yes|1982|7|24}}"}],"MedalCompetition":[{}],"chú thích web":[{"{{chú thích web|author":"Khương Xuân|title=CLB Nam Định thay HLV trưởng sau khi cổ động viên dọa bỏ đội|url=https:\/\/tuoitre.vn\/clb-nam-dinh-thay-hlv-truong-sau-khi-co-dong-vien-doa-bo-doi-20220824163502349.htm|publisher=Tuổi trẻ online|date=2022-08-24}}"}],"Bài cùng tên":[{}],"MedalSport":[{}],"thời gian sống":[{}],"Medal":[{}],"tham khảo":[{}],"Mô tả ngắn":[{}],"fb":[{}]}}