{"19611142":{"Chú thích web":[{"{{Chú thích web|url":"https:\/\/2019.wechoice.vn\/hang-muc\/giai-tri.htm|tựa đề=Hạng mục Giải Trí - WeChoice Awards 2019|website=2019.wechoice.vn|url-status=live|ngày truy cập=2022-02-03|archive-date=2022-02-01|archive-url=https:\/\/web.archive.org\/web\/20220201132511\/https:\/\/2019.wechoice.vn\/hang-muc\/giai-tri.htm}}"}],"Thứ tự chương trình TV":[{"{{Thứ tự chương trình TV|Broadcasting station":"[[VTV3]]|Broadcasting slot=Phim truyền hình<br> 21:30 thứ Hai, thứ Ba (26\/11\/2018 - 2\/4\/2019)|Previous program=''[[Quỳnh búp bê]]''<br\/>(3\/9 - 20\/11\/2018)|Title=''Chạy trốn thanh xuân''<br\/>(26\/11\/2018 - 2\/4\/2019)|Next program=''[[Nàng dâu order]]''<br\/>(8\/4 - 16\/7\/2019)}}"}],"won":[{"{{won|place":"3|Bằng khen}}"}],"Thông tin truyền hình\n":[{"Nhan đề nghiêng":"Chạy trốn thanh xuân","tên khác":"'''''Oan gia xóm trọ'''''","số tập":"36","phát sóng cuối":"2 tháng 4 năm 2019","ngôn ngữ":"[[tiếng Việt]] }}","đơn vị sản xuất":"[[Trung tâm Phim truyền hình Việt Nam]], [[Đài Truyền hình Việt Nam]]","diễn viên":"Lưu Đê Ly<br>[[Huỳnh Anh]]<br>[[Mạnh Trường]]<br>[[Phan Minh Huyền]]<br>[[Chiều Xuân|NSƯT Chiều Xuân]]<br>[[Hoàng Hải (diễn viên)|NSƯT Hoàng Hải]]<br>[[Bình An (diễn viên)|Bình An]]","hình":"Chạy trốn thanh xuân.png","kịch bản":"Thủy Vũ<br>Mai Diệp","network":"[[VTV3]]","followed_by":"''[[Nàng dâu order]]''","phát sóng đầu":"26 tháng 11 năm 2018","định dạng":"[[Phim truyền hình]]","đạo diễn":"Vũ Minh Trí<br>Nguyễn Đức Hiếu","thời lượng":"45 phút\/tập (không bao gồm [[quảng cáo]])","preceded_by":"''[[Quỳnh búp bê]]''","genre":"[[Tâm lý xã hội]]<br>[[Tình cảm]]<br>[[Thanh xuân]]","giám đốc sản xuất":"[[Đỗ Thanh Hải|NSƯT Đỗ Thanh Hải]]","quốc gia":"{{VIE}}"}],"tham khảo":[{}]}}