{"2184133":{"Chú thích web ":[{"{{Chú thích web |url":"http:\/\/gialam.gov.vn\/gialam\/portal\/News-details\/159\/1159\/Dinh-Dong-Du-Ha.html |ngày truy cập=2018-12-03 |tựa đề=ĐÌNH ĐÔNG DƯ HẠ - HÀ NỘI |archive-date=2017-09-22 |archive-url=https:\/\/web.archive.org\/web\/20170922100029\/http:\/\/gialam.gov.vn\/gialam\/portal\/News-details\/159\/1159\/Dinh-Dong-Du-Ha.html |url-status=dead }}"}],"chú thích web ":[{"{{chú thích web | url":"http:\/\/dhthuanthanh.com\/vi\/article\/thuy-to-viet-nam.aspx | tiêu đề = Thủy tổ Việt Nam | author = | ngày = | ngày truy cập = 17 tháng 2 năm 2015 | nơi xuất bản = | ngôn ngữ = | archive-date = 2013-06-09 | archive-url = https:\/\/web.archive.org\/web\/20130609172703\/http:\/\/dhthuanthanh.com\/vi\/article\/thuy-to-viet-nam.aspx| url-status=dead }}"}]}}