{"18465316":{"chú thích web":[{"{{chú thích web|url":"https:\/\/dantri.com.vn\/giao-duc-huong-nghiep\/fpt-school-da-nang-dinh-huong-nang-luc-hoc-tap-toan-cau-20170628075251455.htm|tiêu đề=FPT School Đà Nẵng - Định hướng năng lực học tập toàn cầu|author=|ngày=2017-06-28|website=[[Dân trí (báo)|Báo điện tử Dân Trí]]|ngôn ngữ=|nơi xuất bản=|url-status=live|ngày truy cập=8 tháng 8 năm 2021}}"}],"Chú thích web":[{"{{Chú thích web|url":"https:\/\/tuoitre.vn\/news-20180525110920682.htm|tựa đề=Đà Nẵng thêm 3 trường liên cấp, bắt đầu tuyển sinh năm nay|tác giả=Đoàn Cường|họ=|tên=|ngày=2018-05-25|website=[[Tuổi Trẻ (báo)|Tuổi Trẻ Online]]|ngôn ngữ=vi|url-status=live|ngày truy cập=2021-08-07}}"}],"tham khảo":[{}],"Date":[{}]}}