{"19741251":{"coord missing":[{}],"tham khảo":[{}],"cite book":[{"{{cite book|last":"Pham|first=Sherisse|title=Frommer's Vietnam: With Angkor Wat|url=https:\/\/books.google.com\/books?id=S_goLURt0AgC&pg=PA89|date=31 December 2009|publisher=John Wiley & Sons|isbn=978-0-470-59567-1|page=89}}"}],"cite web":[{"{{cite web|url":"http:\/\/travel.cnn.com\/explorations\/escape\/ultimate-asian-city-adventures\/pocket-guide-hanois-old-quarter-379111|title=Pocket guide to Hanoi's Old Quarter |publisher=CNN|accessdate=19 June 2015}}"}]}}