{"15658246":{"Các chủ đề":[{}],"Chú thích báo ":[{"{{Chú thích báo |tên bài":"Hồ Ngọc Hà khoe vòng 1 quyến rũ khi trở lại \"ghế nóng\" gameshow|url = https:\/\/www.yan.vn\/ho-ngoc-ha-lap-lo-vong-1-ngay-tro-lai-ghe-nong-gameshow-213851.html|công trình = Yan News|}}"}],"tham khảo":[{}],"Thông tin truyền hình \n":[{"image":"","website":"https:\/\/www.facebook.com\/GuongMatThanQuenOfficial\/ }}","presenter":"[[Thanh Bạch]]","show_name":"Gương mặt thân quen (mùa 7)","channel":"[[VTV3]]","last_aired":"<br>18 tháng 1, 2020","runtime":"88\u2013108 phút","first_aired":"2 tháng 11, 2019","followed_by":"''[[Gương mặt thân quen (mùa 8)|Mùa 8]]''","related":"[[Your Face Sounds Familiar]]<br\/> [[Gương mặt thân quen Nhí]]","preceded_by":"''[[Gương mặt thân quen (mùa 6)|Mùa 6]]''","num_episodes":"12 <ref>{{Chú thích báo |tên bài = Hồ Ngọc Hà khoe vòng 1 quyến rũ khi trở lại \"ghế nóng\" gameshow|url = https:\/\/www.yan.vn\/ho-ngoc-ha-lap-lo-vong-1-ngay-tro-lai-ghe-nong-gameshow-213851.html|công trình = Yan News|}}<\/ref>","judges":"[[Quang Linh]] <br\/> [[Hồ Ngọc Hà]] <br\/> [[Đức Thịnh (đạo diễn)|Đức Thịnh]] & [[Thanh Thúy (sinh 1982)|Thanh Thúy]] (tập 1, 6\u20137) <br\/> [[Kim Xuân]] (tập 2, 5, 9) <br\/> Đức Hải (tập 3\u20134) <br\/> [[Kim Tử Long]] (tập 8, 10\u201311) <br> [[Lê Hoàng]] (tập 12)"}],"colorbox":[{}],"Webarchive":[{"{{Webarchive|url":"https:\/\/web.archive.org\/web\/20170608060123\/http:\/\/guongmatthanquen.vn\/ |date=2017-06-08 }}"}]}}