{"1751794":{"Liên kết hỏng":[{"{{Liên kết hỏng|date":"ngày 9 tháng 5 năm 2021|bot=InternetArchiveBot}}"}],"Thông tin tu sĩ Phật giáo\n":[{"trường phái":"[[Đại thừa]]","pháp danh":"Thiệt Diệu 實耀","nơi an táng":"Chân núi Thiên Thai, Huế","tiền tố":"Thiền sư","hình":"Liễu Quán.JPG","lưu phái":"[[Lâm Tế tông]]","tông phái":"[[Thiền tông]]","nơi mất":"[[Chùa Viên Thông]], xã [[Thủy An]], thành phố [[Huế]]","thụy":"Chính Giác - Viên Ngộ Hòa Thượng","tên gốc":"了觀","ngày mất":"1742","nơi sinh":"làng Bạch Mã, huyện [[Đồng Xuân]], tỉnh [[Phú Yên]]","tên":"Liễu Quán","ngày sinh":"1667","chú thích hình":"Tháp mộ Tổ sư Liễu Quán ở chân núi Thiên Thai, Huế","quốc gia":"[[Việt Nam]] }}","pháp tự":"Liễu Quán 了觀","sư phụ":"[[Tế Viên]], [[Giác Phong]], [[Thạch Liêm]], [[Từ Lâm]]"}],"thời gian sống":[{"{{thời gian sống|sinh":"1667|mất=1203}}"}],"Webarchive":[{"{{Webarchive|url":"https:\/\/web.archive.org\/web\/20110911203254\/http:\/\/www.chuabuuminh.vn\/su-lieu\/chan-dung-nhan-vat\/76C213_thien_su_lieu_quan.aspx|date=2011-09-11}}"}]}}