{"3410716":{"chú thích web":[{"{{chú thích web|url":"http:\/\/hanchi.ihp.sinica.edu.tw\/mql\/login.html |title = Veritable Records of the Ming Dynasty, Joseon Dynasty & Qing Dynasty |author = Academia Sinica |language = zh}}"}],"zh ":[{"{{zh |t":"明實錄 |s = 明实录 }}"}],"ill":[{}],"lang":[{}],"Tham khảo":[{}],"Wikisource-zh":[{}],"chú thích web ":[{"{{chú thích web |url":"http:\/\/sillok.history.go.kr\/mc\/main.do |language = ko,zh |title = Veritable Records of the Ming, Veritable Records of the Qing|author=National Institute of Korean History}}"}]}}