{"522693":{"chú thích web":[{"{{chú thích web|title":"Cựu tuyển thủ Nguyễn Hữu Thắng: Chạm tay vào nỗi nhớ|url=https:\/\/bongdaplus.vn\/v-league\/cuu-tuyen-thu-nguyen-huu-thang-cham-tay-vao-noi-nho-3063652008.html|publisher=VnExpress|date=2020-08-02}}"}],"Thời gian sống":[{}],"bài cùng tên":[{}],"người khác 3":[{}],"ngày sinh và tuổi":[{"{{ngày sinh và tuổi|1980|06|22|df":"y}}"}],"Thông tin tiểu sử bóng đá\n":[{"nationalyears1":"2003\u20132007","birth_name":"Nguyễn Hữu Thắng","nationalteam1":"[[Đội tuyển bóng đá quốc gia Việt Nam|Việt Nam]]","birth_date":"{{ngày sinh và tuổi|1980|06|22|df=y}}","youthclubs1":"[[Câu lạc bộ bóng đá Becamex Bình Dương|Becamex Bình Dương]]","birth_place":"[[Dĩ An]], [[Bình Dương]], Việt Nam","years3":"2009\u20132013","years2":"2008","nationalcaps1":"13","years1":"2004\u20132007","clubs1":"[[Câu lạc bộ bóng đá Becamex Bình Dương|Becamex Bình Dương]]","clubs2":"[[Câu lạc bộ bóng đá Xi măng The Vissai Ninh Bình|Vissai Ninh Bình]]","clubs3":"[[Câu lạc bộ bóng đá Becamex Bình Dương|Becamex Bình Dương]]","youthyears1":"","currentclub":"","clubnumber":"","name":"Nguyễn Hữu Thắng","position":"[[Tiền vệ (bóng đá)|Tiền vệ]]","nationalgoals1":"1 }}","height":"1,84 m"}],"NFT":[{}]}}