{"199801":{"Chú thích web ":[{"{{Chú thích web |url":"http:\/\/www.larousse.fr\/encyclopedie\/litterature\/Vi%C3%AAt-Nam_%3Csmall%3E%5BLITT%C3%89RATURE%5D%3Csmall%3E_L_histoire_du_Vi%C3%AAt-nam_a_tr%C3%A8s_largement_marqu%C3%A9_de_son_empreinte\/177800 |ngày truy cập=2009-06-08 |tựa đề=Viêt-Nam |archive-date=2009-09-14 |archive-url=https:\/\/web.archive.org\/web\/20090914084109\/http:\/\/www.larousse.fr\/encyclopedie\/litterature\/Vi%C3%AAt-Nam_%3Csmall%3E&#91;LITT%C3%89RATURE&#93;%3Csmall%3E_L_histoire_du_Vi%C3%AAt-nam_a_tr%C3%A8s_largement_marqu%C3%A9_de_son_empreinte\/177800 |url-status=dead }}"}],"ngày mất và tuổi":[{}],"ngày sinh":[{}],"tham khảo":[{}],"Thông tin nghệ sĩ\n":[{"hạng mục 1":"Văn học nghệ thuật","birthdate":"{{ngày sinh|1923|8|1}}","influenced":"","caption":"Chân dung họa sĩ lúc trẻ","training":"[[Trường Đại học Mỹ thuật Việt Nam|Cao đẳng Mỹ thuật Đông Dương]]","deathdate":"{{ngày mất và tuổi|1988|12|16|1923|8|1}}","năm 1":"1996","famous works":"","giải thưởng 1":"[[Giải thưởng Hồ Chí Minh]]","tác phẩm hội họa":"","alias":"","image":"Nguyensang.jpg","tác phẩm hội họa nổi bật":"''Kết nạp Đảng ở Điện Biên Phủ'' }}","imagesize":"200px","influenced by":"","tên gốc":"","nationality":"{{VNM}}","field":"[[sơn dầu]] và [[sơn mài]]","birthname":"Nguyễn Sáng","tên":"Nguyễn Sáng","deathplace":"[[Thành phố Hồ Chí Minh]], [[Việt Nam]]","location":"[[Mỹ Tho (tỉnh)|Mỹ Tho]], [[Nam Kì]], [[Liên Bang Đông Dương]]","patrons":"","movement":"","nền":"họa sĩ"}],"Webarchive":[{"{{Webarchive|url":"https:\/\/web.archive.org\/web\/20080229054932\/http:\/\/www.tiengiang.gov.vn\/xemtin.asp?idcha=997&cap=3&id=1235 |date=2008-02-29 }}"}]}}