{"3171342":{"Chú thích web":[{"{{Chú thích web|url":"http:\/\/thethaovanhoa.vn\/bong-da-viet\/pct-vff-nguyen-lan-trung-ong-pho-7-trong-1-n20100219122853209.htm|title = PCT VFF Nguyễn Lân Trung: Ông \"Phó 7 trong 1\"}}"}],"flatlist":[{}],"Wiki hóa":[{"{{Wiki hóa|date":"tháng 1\/2022}}"}],"tham khảo":[{}],"Infobox Scientist\n":[{"image":"NguyenLanTrung_2020.jpg","occupation":"Nhà khoa học, nhà giáo, nhà quản lý thể thao","birth_date":"1953","caption":"Nguyễn Lân Trung,<br \/>tháng 12 năm 2020 tại Hà Nội","birth_place":"[[Mỹ Hào]], [[Hưng Yên]]","imagesize":"200px","spouse":"","death_date":"","nationality":"{{VIE}}","field":"Chuyên gia ngôn ngữ tiếng Pháp","partner":"","children":"{{flatlist| * Nguyễn Ngọc Lưu Ly (1981) * Nguyễn Lân Trung Anh (1989) }} }}","known_for":"{{flatlist| *Phó Chủ tịch [[Liên đoàn Bóng đá Việt Nam]] *Phó Hiệu trưởng Trường Đại học Ngoại ngữ, [[Đại học Quốc gia Hà Nội]] *Phó Chủ tịch kiêm Tổng Thư ký Hội hữu nghị Việt \u2013 Pháp }}","name":"Nguyễn Lân Trung","death_place":""}]}}