{"1336700":{"Thông tin nhân vật hoàng gia\n":[{"tước hiệu":"Kính phi","hình":"","nơi mất":"[[Đông Kinh]]","tên hiệu":"","chữ ký":"}}","chồng":"[[Lê Hiến Tông]]","cỡ hình":"250px","thụy hiệu":"''không có''","chức vị":"","tại vị":"","mất":"?","đăng quang":"","cha":"","học vấn":"","thời gian của niên hiệu":"","tôn giáo":"","tên tự":"","tôn hiệu":"","sinh":"?","nơi an táng":"","tước vị thêm":"","hoàng tộc":"[[Nhà Hậu Lê]]","miếu hiệu":"","phối ngẫu":"","nhiếp chính":"","tước vị":"","mẹ":"","ngày an táng":"","nghề nghiệp":"","niên hiệu":"","tên gốc":"阮敬妃","nơi sinh":"Hoa Lăng, [[Thủy Đường]]","tên":"Nguyễn Kính phi","tên đầy đủ":"Nguyễn thị","kế nhiệm":"","con cái":"[[Lê Uy Mục]] (con nuôi)","ghi chú hình":"","tiền nhiệm":""}],"otheruses":[{}]}}