{"13631974":{"Chú thích web":[{"{{Chú thích web|url":"http:\/\/www.daizuwang.com\/Article_Show.asp?ArticleID=4707|tiêu đề=文山州傣族发展历史及宗教习俗（图)}}"}],"Tham khảo":[{}],"Infobox Ethnic group\n":[{"regions":"[[Vân Nam]] (Trung Quốc) <br> [[Lào Cai]] (Việt Nam)","related":"[[Người Bố Y|Bố Y]], [[Người Tày|Tày]] và [[Người Nùng|Nùng]] ([[Việt Nam]]), [[người Choang]] ([[Trung Quốc]]) }}","languages":"[[Tiếng Pa Dí]], [[tiếng Thu Lao]]","religions":"","group":"Người Pa Dí <br> 文山傣族","population":"{{CHN}}: 6.131 (Mã Quan), 4.685 (Văn Sơn) và 2.692 (Ma Lật Pha) <br \/>{{VIE}}: >2000 (Mường Khương)"}],"zh":[{"{{zh|c":"文山傣族|p=Wénshān Dǎizú|hv=Văn Sơn Thái tộc}}"}]}}