{"19672796":{"start date":[{}],"Không nổi bật":[{"{{Không nổi bật|date":"tháng 5\/2023}}"}],"Thông tin truyền hình\n":[{"country":"{{VIE}}","image":"","creator":"[[Trung tâm Phim truyền hình Việt Nam]], [[Đài Truyền hình Việt Nam]]","website":"","color":"","show_name":"Thư giãn cuối tuần","last_aired":"{{end date|2015|4|18}}","format":"[[Hài kịch]]","caption":"","audio_format":"}}","runtime":"","list_episodes":"","first_aired":"{{start date|2010|8|28}}","network":"[[VTV3]]","picture_format":"[[576i]] ([[SDTV]])<br\/>[[720p]] ([[HDTV]])","slogan":""}],"Thiếu nguồn gốc":[{"{{Thiếu nguồn gốc|date":"tháng 5\/2023}}"}],"end date":[{}]}}