{"260081":{"Thông tin trường học\n":[{"nhân viên":"","tên khác":"","tọa độ":"10°21'56.0\"N 106°21'28.6\"E","hiệu trưởng":"PGS-TS Võ Ngọc Hà","hiệu phó":"TS Lê Minh Tùng<br> TS Nguyễn Hoàng Vũ","hình":"","điện thoại":"02733872624<\/br>02736250200","tên bản địa":"","web":"http:\/\/www.tgu.edu.vn","logo":"[[Tập tin:Logo trường Đại học Tiền Giang.svg|242px]]","sinh viên đại học":"","địa chỉ":"119 đường Ấp Bắc, phường 5","quốc gia":"[[Việt Nam]]","email":"daihoctg@tgu.edu.vn","khẩu hiệu":"''Thiết thực - Hiệu quả - Hài Hòa''","tỉnh":"tỉnh [[Tiền Giang]]","ngày thành lập":"6 tháng 6 năm 2005","tài trợ":"","khuôn viên":"","tên tiếng Anh":"Tien Giang University","thành phố":"thành phố [[Mỹ Tho]]","thành viên của":"[[Ủy ban nhân dân tỉnh Tiền Giang (Việt Nam)]]","loại hình":"[[Đại học công lập]]","phó hiệu trưởng":"TS Lê Minh Tùng<\/br> TS Nguyễn Hoàng Vũ","tên":"Trường Đại học Tiền Giang","Fax":"02733884022 }}"}],"Chú thích web":[{"{{Chú thích web|url":"http:\/\/website.tiengiang.gov.vn\/xemtin.asp?idcha=1001&cap=3&id=23430|tiêu đề = Trường đại học Tiền Giang sử dụng cơ sở mới|ngày truy cập = 2015-05-19|archive-date = ngày 20 tháng 5 năm 2015 |archive-url = https:\/\/web.archive.org\/web\/20150520111956\/http:\/\/website.tiengiang.gov.vn\/xemtin.asp?idcha=1001&cap=3&id=23430}}"}],"dablink":[{}],"Liên kết hỏng":[{"{{Liên kết hỏng|date":"ngày 25 tháng 5 năm 2021 |bot=InternetArchiveBot }}"}],"tham khảo":[{}]}}