{"92177":{"Thứ tự kế vị\n":[{"chức vụ":"Vua [[nhà Trần]]","sau":"Không có","năm":"[[1398]]-[[1400]] }}","trước":"[[Trần Thuận Tông]]"}],"Thiếu nguồn gốc":[{"{{Thiếu nguồn gốc|date":"tháng 10\/2022}}"}],"notelist":[{}],"efn":[{}],"số năm theo năm và ngày":[{}],"Thông tin nhân vật hoàng gia\n":[{"tước hiệu":"","thêm":"vietnam","kiểu tại vị":"Trị vì","hình":"","nơi mất":"","tên hiệu":"","chữ ký":"","thụy hiệu":"","chức vị":"[[Nhà Trần|Hoàng đế Đại Việt]]","kiểu nhiếp chính":"Phụ chính","mất":"?","tại vị":"[[15 tháng 3]] năm [[1398]] \u2013 [[15 tháng 3]] năm [[1400]]<br>({{số năm theo năm và ngày|1398|3|15|1400|3|15}})<timeline> ImageSize = width:200 height:50 PlotArea = width:170 height:30 left:14 bottom:20 TimeAxis = orientation:horizontal DateFormat = yyyy Period = from:1225 till:1400 AlignBars = early ScaleMajor = increment:175 start:1225 Colors = id:canvas value:rgb(1,1,0.97) BackgroundColors = canvas:canvas PlotData = width:15 color:black bar:era from:start till:end bar:era from:1398 till:1400 color:red <\/timeline>","đăng quang":"","cha":"[[Trần Thuận Tông]]","học vấn":"","Kích thước hình ảnh":"486 x 743 }}","tôn giáo":"","thời gian của niên hiệu":"","tên tự":"","tôn hiệu":"","sinh":"[[1396]]","nơi an táng":"","tước vị thêm":"","hoàng tộc":"[[Nhà Trần]]","miếu hiệu":"","phối ngẫu":"","nhiếp chính":"[[Hồ Quý Ly]]","kiểu tên đầy đủ":"Tên húy","tước vị":"[[Vua Việt Nam]]","mẹ":"[[Khâm Thánh hoàng hậu|Khâm Thánh Hoàng hậu]]","ngày an táng":"","kiểu hoàng tộc":"Triều đại","nghề nghiệp":"","niên hiệu":"Kiến Tân (建新)","tên gốc":"陳少帝","nơi sinh":"","tên":"Trần Thiếu Đế","tên đầy đủ":"Trần An (陳[[Tập tin:安火缺字.svg|15px]])","kế nhiệm":"<font color=\"red\">'''Triều đại nhà Trần sụp đổ'''<br>[[Hồ Quý Ly]] (Nhà Hồ)","con cái":"","ghi chú hình":"","tiền nhiệm":"[[Trần Thuận Tông]]"}],"Navboxes\n":[{"list1":"<span>{{Đầu hộp}} {{Thứ tự kế vị","chức vụ":"Vua [[nhà Trần]]","sau":"Không có","năm":"[[1398]]-[[1400]] }} {{Cuối hộp}} {{Vua nhà Trần}} }}","trước":"[[Trần Thuận Tông]]","title":"Trần Thiếu Đế"}]}}