{"503166":{"Chú thích web":[{"{{Chú thích web|url":"https:\/\/thuvienphapluat.vn\/van-ban\/bat-dong-san\/Nghi-dinh-50-2003-ND-CP-thanh-lap-xa-thuoc-huyen-Tan-Hung-Thanh-Hoa-Duc-Hue-va-Thu-Thua-tinh-Long-An-6610.aspx|tựa đề=Nghị định số 50\/2003\/NĐ-CP về việc thành lập xã thuộc các huyện Tân Hưng, Thạnh Hóa, Đức Huệ và Thủ Thừa, tỉnh Long An|tác giả=|họ=|tên=|ngày=|website=|url lưu trữ=|ngày lưu trữ=|url hỏng=|ngày truy cập=}}"}],"bài cùng tên":[{}],"Maplink":[{"{{Maplink|frame":"yes|plain=yes|frame-width=280|frame-align=center|type=shape|fill=#ffffff|fill-opacity=0|stroke-width=3}}"}],"Thông tin đơn vị hành chính Việt Nam":[{"bản đồ 1":"{{Maplink|frame=yes|plain=yes|frame-width=280|frame-align=center|type=shape|fill=#ffffff|fill-opacity=0|stroke-width=3}}","diện tích":"39,66 km²","vùng":"[[Đồng bằng sông Cửu Long]]","dân số":"3.399 người","thành lập":"1981<ref name=71-HĐBT\/>","tỉnh":"[[Long An]]","huyện":"[[Thủ Thừa]]","trụ sở UBND":"","mật độ dân số":"86 người\/km²","hình":"","vĩ độ":"10.648786","kinh độ":"106.376023","thời điểm dân số":"2003","mã hành chính":"28042<ref>[https:\/\/danhmuchanhchinh.gso.gov.vn\/ Tổng cục Thống kê]<\/ref>","tên":"Tân Thành","mã bưu chính":"}}","ghi chú hình":"","vị trí lấy tọa độ":""}],"tham khảo":[{}]}}