{"23575":{"citation ":[{"{{citation |url":"http:\/\/hk.drsunyatsen.museum\/download\/brochure_07_a.pdf |title=孫中山先生史蹟徑 &#91;Dr Sun Yat-sen Historical Trail&#93|language=zh, tiếng Anh |author=中西區區議會 &#91;Central & Western District Council&#93|work=[http:\/\/hk.drsunyatsen.museum Dr. Sun Yat-sen Museum] |publisher=[[Dr Sun Yat-sen Museum|Dr. Sun Yat-sen Museum]] |location=Hong Kong, China |page=30 |year=2006 |access-date=ngày 15 tháng 9 năm 2012 |archive-date=2012-02-24 |archive-url=https:\/\/web.archive.org\/web\/20120224001159\/http:\/\/hk.drsunyatsen.museum\/download\/brochure_07_a.pdf }}"}],"Chú thích web ":[{"{{Chú thích web |url":"http:\/\/www.hsstudyc.org.hk\/en\/tripod_en\/en_tripod_162_05.html#_ftnref2 |ngày truy cập=2014-01-02 |tựa đề=Sun Yat-sen and Christianity |archive-date=2019-05-03 |archive-url=https:\/\/web.archive.org\/web\/20190503064848\/http:\/\/hsstudyc.org.hk\/en\/tripod_en\/en_tripod_162_05.html#_ftnref2 |url-status=dead }}"}],"Gutenberg author ":[{"{{Gutenberg author |id":"43141}}"}],"Internet Archive author ":[{"{{Internet Archive author |sname":"Sun Yat-sen }}"}],"Infobox officeholder 1\n":[{"image":"Sun Yat Sen portrait 2 (9to12).jpg","predecessor2":"''' Không'''","occupation":"[[Thầy thuốc]], [[Chính trị gia|Nhà chính trị]], [[Nhà cách mạng]], [[Nhà văn]]","successor":"[[Viên Thế Khải]] (Tổng thống đầu tiên)","term_end2":"[[2 tháng 3]] năm [[1925]]<br\/>({{số năm theo năm và ngày|1919|10|10|1925|3|2}})","birth_date":"{{birth date|1866|11|12|mf=y}}","blank1":"Tôn giáo","data1":"","caption":"Tôn Văn năm 1911","successor2":"[[Trương Nhân Kiệt]] }}","birth_place":"làng Thuý Hanh, trấn [[Trung Sơn (thành phố)|Hương Sơn]], phủ [[Quảng Châu]], tỉnh [[Quảng Đông]], [[Nhà Thanh|Đại Thanh]]","office":"[[Nguyên thủ quốc gia Trung Hoa Dân quốc|Đại Tổng thống Lâm thời Trung Hoa Dân Quốc]]","predecessor":"[[Phổ Nghi]] ([[danh sách vua Trung Quốc|Hoàng đế Trung Hoa]])","spouse":"[[Lư Mộ Trinh]] (1885-1915) <br \/>[[Tống Khánh Linh]] (1915-1925)","death_date":"{{death date and age|1925|3|12|1866|11|12|mf=y}}","term_start2":"[[10 tháng 10]] năm [[1919]]","nationality":"[[Trung Hoa Dân Quốc (1912-1949)|Trung Quốc]]","alma_mater":"[[Trường đại học Tây Y Hồng Kông cho người Hoa]] (香港華人西醫書院, ''Hương Cảng Hoa nhân Tây y thư viện'')","term_start":"[[1 tháng 1]] năm [[1912]]","name":"Tôn Trung Sơn <br \/> {{lang|zh-hant|孫中山}}","term_end":"[[10 tháng 3]] năm [[1912]]<br\/>({{số năm theo năm và ngày|1912|1|1|1912|3|10}})","death_place":"[[Bắc Kinh]], [[Trung Hoa Dân Quốc (1912-1949)|Trung Hoa Dân Quốc]]","order2":"Chủ tịch [[Trung Quốc Quốc Dân Đảng]]","party":"[[Trung Quốc Quốc Dân Đảng|Quốc Dân Đảng (KMT)]]"}],"số năm theo năm và ngày":[{}],"chú thích web ":[{"{{chú thích web |url":"http:\/\/www.chinanews.com.cn\/n\/2003-12-04\/26\/376869.html |script-title=zh:浓浓乡情系中原\u2014访孙中山先生孙女孙穗芳博士&nbsp;\u2013 我的祖父是客家人 |website=chinanews.com.cn |date = ngày 4 tháng 12 năm 2003}}"}],"Thời gian sống":[{"{{Thời gian sống|sinh":"1866|mất=1925|tên=Tôn Dật Tiên}}"}],"Chú thích web":[{"{{Chú thích web|tác giả 1":"Quốc Phương|tiêu đề=Tam Dân chủ nghĩa vẫn còn thời sự với VN|url=http:\/\/www.bbc.com\/vietnamese\/vietnam\/2011\/10\/111007_tontrungson_profngoc.shtml|website=BBC tiếng Việt|ngày tháng=2011-10-07}}"}],"TĐBKVN":[{}],"thể loại Commons":[{}],"chú thích sách":[{"{{chú thích sách|tiêu đề":"[[Chủ nghĩa Tam Dân]]|tác giả=Tôn Trung Sơn|translator=Nguyễn Như Diệm; Nguyễn Tu Tri|địa điểm=|nhà xuất bản=|năm=1995|id=}}"}],"death date and age":[{"{{death date and age|1925|3|12|1866|11|12|mf":"y}}"}],"tham khảo":[{}],"lang":[{}],"birth date":[{"{{birth date|1866|11|12|mf":"y}}"}],"Britannica":[{}]}}