{"3431788":{"tham khảo":[{}],"Infobox military conflict\n":[{"date":"[[2 tháng 12]] năm [[1968]]","partof":"[[Chiến tranh Việt Nam]]","commander1":"","commander2":"[[Tập tin:FNL Flag.svg|23px]] Lê Minh Xuân<br\/>[[Tập tin:FNL Flag.svg|23px]] [[Bành Văn Trân]] (Năm Vững)<br\/>[[Tập tin:FNL Flag.svg|23px]] [[Nguyễn Văn Kịp]] (Đồng Đen)","casualties1":"'''''Nguồn Quân Giải phóng''''': 260 [[máy bay]] các loại<br\/>1 kho [[bom]] 300 tấn<br\/>13 [[xe quân sự]]<br\/>hơn 600 [[sĩ quan]] và lính Mỹ, Việt Nam Cộng hòa<ref name=antg>http:\/\/antg.cand.com.vn\/Tu-lieu-antg\/Co-mot-tran-danh-tra-thu-cho-Ha-Noi-381282\/<\/ref> '''''Nguồn Mỹ''''':<br\/>3 lính Mỹ, 3 lính VNCH thiệt mạng<br\/>15 lính Mỹ và 4 lính VNCH bị thương<br\/>20 máy bay bị phá hủy","casualties2":"'''''Nguồn Mỹ''''': 18 lính }}","result":"[[Quân Giải phóng miền Nam Việt Nam]] chiến thắng<ref name=antg\/>","combatant1":"[[Tập tin:Flag of South Vietnam.svg|22px]] [[Việt Nam Cộng hòa]]<br\/>[[Tập tin:Flag of the United States.svg|22px]] [[Hoa Kỳ|Mỹ]]","combatant2":"[[Tập tin:FNL Flag.svg|23px]] [[Quân Giải phóng miền Nam Việt Nam]]","strength1":"","strength2":"1 Tiểu đoàn thuộc Sư đoàn đặc công F100","place":"[[Sân bay quốc tế Tân Sơn Nhất|Sân bay Tân Sơn Nhất]], [[Việt Nam]]","conflict":"Cuộc tấn công sân bay Tân Sơn Nhất (1968)"}]}}