{"11762917":{"chú thích web":[{"{{chú thích web|title":"DANH SÁCH ĐẠI BIỂU QUỐC HỘI KHÓA I TỈNH QUẢNG BÌNH (1946-1960)|url=https:\/\/dbqh.quangbinh.gov.vn\/3cms\/doan-dai-bieu-quoc-hoi-tinh-quang-binh-khoa-i.htm|access-date = ngày 27 tháng 6 năm 2020}}"}],"Thời gian sống":[{}],"chú thích web ":[{"{{chú thích web |url":"http:\/\/dantri.com.vn\/xa-hoi\/chuyen-tim-mo-than-phu-dai-tuong-vo-nguyen-giap-1384451497.htm |tiêu đề =Chuyện tìm mộ thân phụ Đại tướng Võ Nguyên Giáp |author = |ngày = |nhà xuất bản = |ngày truy cập =2018-01-04 |ngôn ngữ = |archiveurl = |ngày lưu trữ = 2018-01-04}}"}]}}