{"635295":{"Chú thích web":[{"{{Chú thích web|url":"https:\/\/thuvienphapluat.vn\/van-ban\/bo-may-hanh-chinh\/Nghi-quyet-835-NQ-UBTVQH14-2019-thanh-lap-phuong-Quang-Thanh-thi-xa-Gia-Nghia-Dak-Nong-433007.aspx|tựa đề= Nghị quyết 835\/NQ-UBTVQH14 năm 2019 về việc thành lập phường Quảng Thành thuộc thị xã Gia Nghĩa và thành phố Gia Nghĩa thuộc tỉnh Đắk Nông|ngày= 17 tháng 12 năm 2019 |website= Thư viện pháp luật }}"}],"coord":[{"{{coord| 11.9383763 | 107.6660358 | type:landmark| format":"dms| name= Thác Gia Vĩ}}"}],"Chú thích web ":[{"{{Chú thích web |url":"http:\/\/cucthongkedaknong.gov.vn\/MediaUploader\/anpham\/TDT%20Dan%20so%202019%20Dak%20Nong.rar |title = Dân số đến 01 tháng 4 năm 2019 - tỉnh Đắk Nông |access-date = ngày 11 tháng 8 năm 2021 |author = Ban chỉ đạo Tổng điều tra dân số và nhà ở trung ương }}"}],"Liên kết hỏng":[{"{{Liên kết hỏng|date":"2022-10-31 |bot=InternetArchiveBot }}"}],"Thông tin đơn vị hành chính Việt Nam ":[{"diện tích":"93,52 km²","vùng":"[[Tây Nguyên]]","dân số":"10.361 người<ref name=DAKNONG2019\/>","thành lập":"","tỉnh":"[[Đắk Nông]]","trụ sở UBND":"","mật độ dân số":"111 người\/km²","hình":"Thác Gia Vĩ.jpg","thành phố":"[[Gia Nghĩa]]","vĩ độ":"11.958118","kinh độ":"107.729488","thời điểm dân số":"2019","mã hành chính":"24628<ref>[https:\/\/danhmuchanhchinh.gso.gov.vn\/ Tổng cục Thống kê]<\/ref>","tên":"Đắk Nia","mã bưu chính":"}}","ghi chú hình":"Thác Gia Vĩ"}]}}