{"185752":{"Chú thích web":[{"{{Chú thích web|url":"https:\/\/thuvienphapluat.vn\/van-ban\/Van-hoa-Xa-hoi\/Quyet-dinh-313-VH-VP-xep-hang-nhung-di-tich-danh-thang-canh-toan-mien-Bac-19864.aspx|title=Quyết định 313-VH\/VP xếp hạng những di tích, danh thắng cảnh toàn miền Bắc|website=Thư viện pháp luật}}"}],"Toàn cảnh":[{}],"thể loại Commons":[{}],"Tham khảo ":[{"{{Tham khảo |colwidth":"27em}}"}],"Liên kết hỏng":[{"{{Liên kết hỏng|date":"ngày 1 tháng 6 năm 2021 |bot=InternetArchiveBot }}"}],"Thông tin đền Việt Nam\n":[{"ngày nhận":"28 tháng 4 năm 1962","bản đồ 1":"","tên khác":"","chú thích":"Đường chính đạo","hình":"Đền Lê Đại Hành, chính đạo.JPG","điện thoại":"","đóng cửa":"","công trạng":"đánh tan [[nhà Tống|quân Tống]], lập nhà [[nhà Tiền Lê|Tiền Lê]]","di tích":"","kinh giây":"","kinh độ":"105.9056228","web":"","tên di tích":"Khu vực núi Trường Yên và đền vua Đinh, đền vua Lê","mất":"[[1005]]","vĩ phút":"","xây mới":"","ghi chú bản đồ 1":"","địa chỉ":"tỉnh [[Ninh Bình]]","tôn tạo":"","vĩ giây":"","một phần của":"[[Cố đô Hoa Lư]]<ref>Quyết định 08\/2001\/QĐ-BVHTT ngày 13 tháng 3 năm 2001 của Bộ Văn hóa-Thông tin<\/ref> }}","sinh":"[[941]]","loại đền":"","thành lập":"","kinh phút":"","lễ hội":"","thánh tích":"","tước vị":"Đại Hành Hoàng Đế","tên thần":"[[Lê Đại Hành|Lê Hoàn]]","cấp di tích":"quốc gia","vĩ độ":"20.2862001","quyết định":"313-VH\/VP<ref>{{Chú thích web|url=https:\/\/thuvienphapluat.vn\/van-ban\/Van-hoa-Xa-hoi\/Quyet-dinh-313-VH-VP-xep-hang-nhung-di-tich-danh-thang-canh-toan-mien-Bac-19864.aspx|title=Quyết định 313-VH\/VP xếp hạng những di tích, danh thắng cảnh toàn miền Bắc|website=Thư viện pháp luật}}<\/ref>","loại di tích 3":"","đối tượng thờ":"tôn thất Tiền Lê","loại di tích 2":"văn hóa","tên":"Đền vua Lê Đại Hành","người sáng lập":"","loại di tích":"lịch sử"}]}}