{"Công an tỉnh Việt Nam":[{"category":"Công an thành phố Cần Thơ"},{"link":"https:\/\/vi.wikipedia.org\/wiki\/Th%E1%BB%83_lo%E1%BA%A1i:C%C3%B4ng_an_th%C3%A0nh_ph%E1%BB%91_C%E1%BA%A7n_Th%C6%A1"},{"category":"Công an thành phố Đà Nẵng"},{"link":"https:\/\/vi.wikipedia.org\/wiki\/Th%E1%BB%83_lo%E1%BA%A1i:C%C3%B4ng_an_th%C3%A0nh_ph%E1%BB%91_%C4%90%C3%A0_N%E1%BA%B5ng"},{"category":"Công an thành phố Hà Nội"},{"link":"https:\/\/vi.wikipedia.org\/wiki\/Th%E1%BB%83_lo%E1%BA%A1i:C%C3%B4ng_an_th%C3%A0nh_ph%E1%BB%91_H%C3%A0_N%E1%BB%99i"},{"category":"Công an thành phố Hải Phòng"},{"link":"https:\/\/vi.wikipedia.org\/wiki\/Th%E1%BB%83_lo%E1%BA%A1i:C%C3%B4ng_an_th%C3%A0nh_ph%E1%BB%91_H%E1%BA%A3i_Ph%C3%B2ng"},{"category":"Công an Thành phố Hồ Chí Minh"},{"link":"https:\/\/vi.wikipedia.org\/wiki\/Th%E1%BB%83_lo%E1%BA%A1i:C%C3%B4ng_an_Th%C3%A0nh_ph%E1%BB%91_H%E1%BB%93_Ch%C3%AD_Minh"},{"category":"Công an thành phố trực thuộc Trung ương"},{"link":"https:\/\/vi.wikipedia.org\/wiki\/Th%E1%BB%83_lo%E1%BA%A1i:C%C3%B4ng_an_th%C3%A0nh_ph%E1%BB%91_tr%E1%BB%B1c_thu%E1%BB%99c_Trung_%C6%B0%C6%A1ng"},{"category":"Công an tỉnh Trà Vinh"},{"link":"https:\/\/vi.wikipedia.org\/wiki\/Th%E1%BB%83_lo%E1%BA%A1i:C%C3%B4ng_an_t%E1%BB%89nh_Tr%C3%A0_Vinh"},{"category":"Giám đốc Công an tỉnh Việt Nam"},{"link":"https:\/\/vi.wikipedia.org\/wiki\/Th%E1%BB%83_lo%E1%BA%A1i:Gi%C3%A1m_%C4%91%E1%BB%91c_C%C3%B4ng_an_t%E1%BB%89nh_Vi%E1%BB%87t_Nam"}]}