{"Quý tộc nhà Trần":[{"category":"Công tước nhà Trần"},{"link":"https:\/\/vi.wikipedia.org\/wiki\/Th%E1%BB%83_lo%E1%BA%A1i:C%C3%B4ng_t%C6%B0%E1%BB%9Bc_nh%C3%A0_Tr%E1%BA%A7n"},{"category":"Hoàng tộc nhà Trần"},{"link":"https:\/\/vi.wikipedia.org\/wiki\/Th%E1%BB%83_lo%E1%BA%A1i:Ho%C3%A0ng_t%E1%BB%99c_nh%C3%A0_Tr%E1%BA%A7n"},{"category":"Hầu tước nhà Trần"},{"link":"https:\/\/vi.wikipedia.org\/wiki\/Th%E1%BB%83_lo%E1%BA%A1i:H%E1%BA%A7u_t%C6%B0%E1%BB%9Bc_nh%C3%A0_Tr%E1%BA%A7n"},{"category":"Vương tước nhà Trần"},{"link":"https:\/\/vi.wikipedia.org\/wiki\/Th%E1%BB%83_lo%E1%BA%A1i:V%C6%B0%C6%A1ng_t%C6%B0%E1%BB%9Bc_nh%C3%A0_Tr%E1%BA%A7n"}]}