{"Việt Nam thập niên 1980":[{"category":"Khởi đầu thập niên 1980 ở Việt Nam"},{"link":"https:\/\/vi.wikipedia.org\/wiki\/Th%E1%BB%83_lo%E1%BA%A1i:Kh%E1%BB%9Fi_%C4%91%E1%BA%A7u_th%E1%BA%ADp_ni%C3%AAn_1980_%E1%BB%9F_Vi%E1%BB%87t_Nam"},{"category":"Việt Nam năm 1980"},{"link":"https:\/\/vi.wikipedia.org\/wiki\/Th%E1%BB%83_lo%E1%BA%A1i:Vi%E1%BB%87t_Nam_n%C4%83m_1980"},{"category":"Việt Nam năm 1981"},{"link":"https:\/\/vi.wikipedia.org\/wiki\/Th%E1%BB%83_lo%E1%BA%A1i:Vi%E1%BB%87t_Nam_n%C4%83m_1981"},{"category":"Việt Nam năm 1982"},{"link":"https:\/\/vi.wikipedia.org\/wiki\/Th%E1%BB%83_lo%E1%BA%A1i:Vi%E1%BB%87t_Nam_n%C4%83m_1982"},{"category":"Việt Nam năm 1983"},{"link":"https:\/\/vi.wikipedia.org\/wiki\/Th%E1%BB%83_lo%E1%BA%A1i:Vi%E1%BB%87t_Nam_n%C4%83m_1983"},{"category":"Việt Nam năm 1984"},{"link":"https:\/\/vi.wikipedia.org\/wiki\/Th%E1%BB%83_lo%E1%BA%A1i:Vi%E1%BB%87t_Nam_n%C4%83m_1984"},{"category":"Việt Nam năm 1985"},{"link":"https:\/\/vi.wikipedia.org\/wiki\/Th%E1%BB%83_lo%E1%BA%A1i:Vi%E1%BB%87t_Nam_n%C4%83m_1985"},{"category":"Việt Nam năm 1986"},{"link":"https:\/\/vi.wikipedia.org\/wiki\/Th%E1%BB%83_lo%E1%BA%A1i:Vi%E1%BB%87t_Nam_n%C4%83m_1986"},{"category":"Việt Nam năm 1987"},{"link":"https:\/\/vi.wikipedia.org\/wiki\/Th%E1%BB%83_lo%E1%BA%A1i:Vi%E1%BB%87t_Nam_n%C4%83m_1987"},{"category":"Việt Nam năm 1988"},{"link":"https:\/\/vi.wikipedia.org\/wiki\/Th%E1%BB%83_lo%E1%BA%A1i:Vi%E1%BB%87t_Nam_n%C4%83m_1988"},{"category":"Việt Nam năm 1989"},{"link":"https:\/\/vi.wikipedia.org\/wiki\/Th%E1%BB%83_lo%E1%BA%A1i:Vi%E1%BB%87t_Nam_n%C4%83m_1989"},{"category":"Chiến tranh Đông Dương thứ ba"},{"link":"https:\/\/vi.wikipedia.org\/wiki\/Th%E1%BB%83_lo%E1%BA%A1i:Chi%E1%BA%BFn_tranh_%C4%90%C3%B4ng_D%C6%B0%C6%A1ng_th%E1%BB%A9_ba"},{"category":"Thể thao Việt Nam thập niên 1980"},{"link":"https:\/\/vi.wikipedia.org\/wiki\/Th%E1%BB%83_lo%E1%BA%A1i:Th%E1%BB%83_thao_Vi%E1%BB%87t_Nam_th%E1%BA%ADp_ni%C3%AAn_1980"},{"category":"Truyền hình Việt Nam thập niên 1980"},{"link":"https:\/\/vi.wikipedia.org\/wiki\/Th%E1%BB%83_lo%E1%BA%A1i:Truy%E1%BB%81n_h%C3%ACnh_Vi%E1%BB%87t_Nam_th%E1%BA%ADp_ni%C3%AAn_1980"}]}