{"Nhân vật bất đồng chính kiến Việt Nam":[{"category":"Nhà hoạt động dân chủ người Việt Nam"},{"link":"https:\/\/vi.wikipedia.org\/wiki\/Th%E1%BB%83_lo%E1%BA%A1i:Nh%C3%A0_ho%E1%BA%A1t_%C4%91%E1%BB%99ng_d%C3%A2n_ch%E1%BB%A7_ng%C6%B0%E1%BB%9Di_Vi%E1%BB%87t_Nam"},{"category":"Nhóm Kiến nghị 72"},{"link":"https:\/\/vi.wikipedia.org\/wiki\/Th%E1%BB%83_lo%E1%BA%A1i:Nh%C3%B3m_Ki%E1%BA%BFn_ngh%E1%BB%8B_72"},{"category":"Tù nhân lương tâm Tổ chức Ân xá Quốc tế bị Việt Nam giam giữ"},{"link":"https:\/\/vi.wikipedia.org\/wiki\/Th%E1%BB%83_lo%E1%BA%A1i:T%C3%B9_nh%C3%A2n_l%C6%B0%C6%A1ng_t%C3%A2m_T%E1%BB%95_ch%E1%BB%A9c_%C3%82n_x%C3%A1_Qu%E1%BB%91c_t%E1%BA%BF_b%E1%BB%8B_Vi%E1%BB%87t_Nam_giam_gi%E1%BB%AF"}]}