{"Địa mạo Khánh Hòa":[{"page":"Thể loại:Sông tại Khánh Hòa"},{"link":"https:\/\/vi.wikipedia.org\/wiki\/Th%E1%BB%83_lo%E1%BA%A1i:S%C3%B4ng_t%E1%BA%A1i_Kh%C3%A1nh_H%C3%B2a"},{"page":"Đá Cá Nhám"},{"link":"https:\/\/vi.wikipedia.org\/wiki\/%C4%90%C3%A1_C%C3%A1_Nh%C3%A1m"},{"page":"Vịnh Cam Ranh"},{"link":"https:\/\/vi.wikipedia.org\/wiki\/V%E1%BB%8Bnh_Cam_Ranh"},{"page":"Đá Ga Ven"},{"link":"https:\/\/vi.wikipedia.org\/wiki\/%C4%90%C3%A1_Ga_Ven"},{"page":"Đá Xu Bi"},{"link":"https:\/\/vi.wikipedia.org\/wiki\/%C4%90%C3%A1_Xu_Bi"},{"page":"Đầm Môn"},{"link":"https:\/\/vi.wikipedia.org\/wiki\/%C4%90%E1%BA%A7m_M%C3%B4n"},{"page":"Đầm Nha Phu"},{"link":"https:\/\/vi.wikipedia.org\/wiki\/%C4%90%E1%BA%A7m_Nha_Phu"},{"page":"Đầm Thủy Triều"},{"link":"https:\/\/vi.wikipedia.org\/wiki\/%C4%90%E1%BA%A7m_Th%E1%BB%A7y_Tri%E1%BB%81u"},{"page":"Thác Tà Gụ"},{"link":"https:\/\/vi.wikipedia.org\/wiki\/Th%C3%A1c_T%C3%A0_G%E1%BB%A5"},{"page":"Thác Yang Bay"},{"link":"https:\/\/vi.wikipedia.org\/wiki\/Th%C3%A1c_Yang_Bay"},{"page":"Quần đảo Trường Sa"},{"link":"https:\/\/vi.wikipedia.org\/wiki\/Qu%E1%BA%A7n_%C4%91%E1%BA%A3o_Tr%C6%B0%E1%BB%9Dng_Sa"},{"page":"Đá Vành Khăn"},{"link":"https:\/\/vi.wikipedia.org\/wiki\/%C4%90%C3%A1_V%C3%A0nh_Kh%C4%83n"},{"page":"Vịnh Nha Trang"},{"link":"https:\/\/vi.wikipedia.org\/wiki\/V%E1%BB%8Bnh_Nha_Trang"},{"page":"Vịnh Vân Phong"},{"link":"https:\/\/vi.wikipedia.org\/wiki\/V%E1%BB%8Bnh_V%C3%A2n_Phong"}]}