{"Khởi đầu năm 1941 ở Campuchia":[{"page":"Thể loại:Khởi đầu năm 1936 ở Campuchia"},{"link":"https:\/\/vi.wikipedia.org\/wiki\/Th%E1%BB%83_lo%E1%BA%A1i:Kh%E1%BB%9Fi_%C4%91%E1%BA%A7u_n%C4%83m_1936_%E1%BB%9F_Campuchia"},{"page":"Thể loại:Khởi đầu năm 1937 ở Campuchia"},{"link":"https:\/\/vi.wikipedia.org\/wiki\/Th%E1%BB%83_lo%E1%BA%A1i:Kh%E1%BB%9Fi_%C4%91%E1%BA%A7u_n%C4%83m_1937_%E1%BB%9F_Campuchia"},{"page":"Thể loại:Khởi đầu năm 1938 ở Campuchia"},{"link":"https:\/\/vi.wikipedia.org\/wiki\/Th%E1%BB%83_lo%E1%BA%A1i:Kh%E1%BB%9Fi_%C4%91%E1%BA%A7u_n%C4%83m_1938_%E1%BB%9F_Campuchia"},{"page":"Thể loại:Khởi đầu năm 1939 ở Campuchia"},{"link":"https:\/\/vi.wikipedia.org\/wiki\/Th%E1%BB%83_lo%E1%BA%A1i:Kh%E1%BB%9Fi_%C4%91%E1%BA%A7u_n%C4%83m_1939_%E1%BB%9F_Campuchia"},{"page":"Thể loại:Khởi đầu năm 1940 ở Campuchia"},{"link":"https:\/\/vi.wikipedia.org\/wiki\/Th%E1%BB%83_lo%E1%BA%A1i:Kh%E1%BB%9Fi_%C4%91%E1%BA%A7u_n%C4%83m_1940_%E1%BB%9F_Campuchia"},{"page":""},{"link":"https:\/\/vi.wikipedia.org"},{"page":"Thể loại:Khởi đầu năm 1942 ở Campuchia"},{"link":"https:\/\/vi.wikipedia.org\/wiki\/Th%E1%BB%83_lo%E1%BA%A1i:Kh%E1%BB%9Fi_%C4%91%E1%BA%A7u_n%C4%83m_1942_%E1%BB%9F_Campuchia"},{"page":"Thể loại:Khởi đầu năm 1943 ở Campuchia"},{"link":"https:\/\/vi.wikipedia.org\/wiki\/Th%E1%BB%83_lo%E1%BA%A1i:Kh%E1%BB%9Fi_%C4%91%E1%BA%A7u_n%C4%83m_1943_%E1%BB%9F_Campuchia"},{"page":"Thể loại:Khởi đầu năm 1944 ở Campuchia"},{"link":"https:\/\/vi.wikipedia.org\/wiki\/Th%E1%BB%83_lo%E1%BA%A1i:Kh%E1%BB%9Fi_%C4%91%E1%BA%A7u_n%C4%83m_1944_%E1%BB%9F_Campuchia"},{"page":"Thể loại:Khởi đầu năm 1945 ở Campuchia"},{"link":"https:\/\/vi.wikipedia.org\/wiki\/Th%E1%BB%83_lo%E1%BA%A1i:Kh%E1%BB%9Fi_%C4%91%E1%BA%A7u_n%C4%83m_1945_%E1%BB%9F_Campuchia"},{"page":"Thể loại:Khởi đầu năm 1946 ở Campuchia"},{"link":"https:\/\/vi.wikipedia.org\/wiki\/Th%E1%BB%83_lo%E1%BA%A1i:Kh%E1%BB%9Fi_%C4%91%E1%BA%A7u_n%C4%83m_1946_%E1%BB%9F_Campuchia"},{"page":"Campuchia thuộc Nhật"},{"link":"https:\/\/vi.wikipedia.org\/wiki\/Campuchia_thu%E1%BB%99c_Nh%E1%BA%ADt"}]}