{"Câu lạc bộ bóng đá Huế":[{"page":"Thể loại:Cầu thủ câu lạc bộ bóng đá Huế"},{"link":"https:\/\/vi.wikipedia.org\/wiki\/Th%E1%BB%83_lo%E1%BA%A1i:C%E1%BA%A7u_th%E1%BB%A7_c%C3%A2u_l%E1%BA%A1c_b%E1%BB%99_b%C3%B3ng_%C4%91%C3%A1_Hu%E1%BA%BF"},{"page":"Câu lạc bộ bóng đá Huế"},{"link":"https:\/\/vi.wikipedia.org\/wiki\/C%C3%A2u_l%E1%BA%A1c_b%E1%BB%99_b%C3%B3ng_%C4%91%C3%A1_Hu%E1%BA%BF"},{"page":"Ninh Văn Bảo"},{"link":"https:\/\/vi.wikipedia.org\/wiki\/Ninh_V%C4%83n_B%E1%BA%A3o"},{"page":"Sân vận động Tự Do"},{"link":"https:\/\/vi.wikipedia.org\/wiki\/S%C3%A2n_v%E1%BA%ADn_%C4%91%E1%BB%99ng_T%E1%BB%B1_Do"}]}