{"Xã, thị trấn thuộc huyện Đoan Hùng":[{"page":"Bằng Doãn"},{"link":"https:\/\/vi.wikipedia.org\/wiki\/B%E1%BA%B1ng_Do%C3%A3n"},{"page":"Bằng Luân"},{"link":"https:\/\/vi.wikipedia.org\/wiki\/B%E1%BA%B1ng_Lu%C3%A2n"},{"page":"Ca Đình"},{"link":"https:\/\/vi.wikipedia.org\/wiki\/Ca_%C4%90%C3%ACnh"},{"page":"Chân Mộng"},{"link":"https:\/\/vi.wikipedia.org\/wiki\/Ch%C3%A2n_M%E1%BB%99ng"},{"page":"Chí Đám"},{"link":"https:\/\/vi.wikipedia.org\/wiki\/Ch%C3%AD_%C4%90%C3%A1m"},{"page":"Đoan Hùng (thị trấn)"},{"link":"https:\/\/vi.wikipedia.org\/wiki\/%C4%90oan_H%C3%B9ng_(th%E1%BB%8B_tr%E1%BA%A5n)"},{"page":"Hợp Nhất"},{"link":"https:\/\/vi.wikipedia.org\/wiki\/H%E1%BB%A3p_Nh%E1%BA%A5t"},{"page":"Hùng Long"},{"link":"https:\/\/vi.wikipedia.org\/wiki\/H%C3%B9ng_Long"},{"page":"Hùng Xuyên"},{"link":"https:\/\/vi.wikipedia.org\/wiki\/H%C3%B9ng_Xuy%C3%AAn"},{"page":"Minh Lương, Đoan Hùng"},{"link":"https:\/\/vi.wikipedia.org\/wiki\/Minh_L%C6%B0%C6%A1ng,_%C4%90oan_H%C3%B9ng"},{"page":"Minh Phú, Đoan Hùng"},{"link":"https:\/\/vi.wikipedia.org\/wiki\/Minh_Ph%C3%BA,_%C4%90oan_H%C3%B9ng"},{"page":"Minh Tiến, Đoan Hùng"},{"link":"https:\/\/vi.wikipedia.org\/wiki\/Minh_Ti%E1%BA%BFn,_%C4%90oan_H%C3%B9ng"},{"page":"Ngọc Quan"},{"link":"https:\/\/vi.wikipedia.org\/wiki\/Ng%E1%BB%8Dc_Quan"},{"page":"Phú Lâm, Đoan Hùng"},{"link":"https:\/\/vi.wikipedia.org\/wiki\/Ph%C3%BA_L%C3%A2m,_%C4%90oan_H%C3%B9ng"},{"page":"Phúc Lai"},{"link":"https:\/\/vi.wikipedia.org\/wiki\/Ph%C3%BAc_Lai"},{"page":"Sóc Đăng"},{"link":"https:\/\/vi.wikipedia.org\/wiki\/S%C3%B3c_%C4%90%C4%83ng"},{"page":"Tây Cốc"},{"link":"https:\/\/vi.wikipedia.org\/wiki\/T%C3%A2y_C%E1%BB%91c"},{"page":"Tiêu Sơn (xã)"},{"link":"https:\/\/vi.wikipedia.org\/wiki\/Ti%C3%AAu_S%C6%A1n_(x%C3%A3)"},{"page":"Vân Du, Đoan Hùng"},{"link":"https:\/\/vi.wikipedia.org\/wiki\/V%C3%A2n_Du,_%C4%90oan_H%C3%B9ng"},{"page":"Vân Đồn (xã)"},{"link":"https:\/\/vi.wikipedia.org\/wiki\/V%C3%A2n_%C4%90%E1%BB%93n_(x%C3%A3)"},{"page":"Vụ Quang"},{"link":"https:\/\/vi.wikipedia.org\/wiki\/V%E1%BB%A5_Quang"},{"page":"Yên Kiện"},{"link":"https:\/\/vi.wikipedia.org\/wiki\/Y%C3%AAn_Ki%E1%BB%87n"}]}