{"Hướng Sủng":[{"snippet":"bản gốc ngày 14 tháng 3 năm 2021. Truy cập 28 tháng 5 năm 2010. ^ a b c \u201C<span class=\"searchmatch\">Huong<\/span> Son Complex of Natural Beauty and Historical Monuments\u201D (bằng tiếng Anh)","pageid":161994,"title":"Danh sách di sản thế giới tại Việt Nam"},{"snippet":"vn\/van-ban\/Bo-may-hanh-chinh\/Nghi-quyet-08-NQ-CP-Thanh-lap-thi-xa-<span class=\"searchmatch\">Huong<\/span>-Thuy-cac-phuong-thi-xa-<span class=\"searchmatch\">Huong<\/span>-Thuy-101380.aspx ^ https:\/\/thuvienphapluat","pageid":11350,"title":"Thị xã (Việt Nam)"},{"snippet":"tháng 10 năm 2020. ^ Hendin, Herbert, Shuiyuan Xiao, Xianyun Li, Tran Thanh <span class=\"searchmatch\">Huong<\/span>, Hong Wang, and Ulrich Hegerl. &quot;Suicide Prevention in Asia: Future Directions","pageid":15383,"title":"Hàn Quốc"},{"snippet":"<span class=\"searchmatch\">huong<\/span>-voi-que-<span class=\"searchmatch\">huong<\/span>-quang-ninh-2326355\/index.htm ^ http:\/\/antg.cand.com.vn\/Tu-lieu-antg\/Chuyen-ve-anh-hung-LLVTNd-Trung-tuong-doan-Sinh-<span class=\"searchmatch\">Huong<\/span>-349527\/","pageid":32033,"title":"T-54\/55"},{"snippet":"năm 2023. ^ https:\/\/baochinhphu.vn\/ngon-ngu-ke-cho-ngon-ngu-xu-doai-xu-<span class=\"searchmatch\">huong<\/span>-2-trong-1-10230995.htm. |title= trống hay bị thiếu (trợ giúp) ^ https:\/\/kienthuc","pageid":45813,"title":"Thạch Thất"},{"snippet":"lược đối ngoại theo hướng nào? - Nga dieu chinh chien luoc doi ngoai theo <span class=\"searchmatch\">huong<\/span> nao? - VOV.VN ^ Rosefielde, Steven (2005). Russia in the 21st Century The","pageid":856,"title":"Nga"},{"snippet":"Encyclopædia Britannica (tiếng Anh) Lê Thái Tổ tại Từ điển bách khoa Việt Nam \u201CNam <span class=\"searchmatch\">Huong<\/span> pagoda and Statue of Le Loi\u201D. 1000 Years Thang Long (VietNamPlus). 29 tháng","pageid":41069,"title":"Lê Thái Tổ"},{"snippet":"Myanmar (AVIM). Sau khi nghỉ hưu, Trần Bắc Hà còn thành lập Công ty Sy Bun <span class=\"searchmatch\">Huong<\/span> (tên theo tiếng Lào) tại bản Kè, huyện Pakse, tỉnh Champasak, Lào. Tính","pageid":11100601,"title":"Trần Bắc Hà"},{"snippet":"ngày kháng chiến&quot; &quot;cô%20du%20kích&quot; http:\/\/www.giadinh.org.vn\/bai-tho-que-<span class=\"searchmatch\">huong<\/span>-cua-nha-tho-giang-nam-va-su-that-ve-co-du-kich\/ Lưu trữ 2017-02-20 tại Wayback","pageid":115580,"title":"Giang Nam (nhà thơ)"},{"snippet":"một quảng cáo miễn phí. Vào năm 2021, QANDA đã cho ra mắt các tính năng bổ <span class=\"searchmatch\">sung<\/span>, bao gồm gói thành viên Premium - cung cấp các bài giảng video không giới","pageid":19544455,"title":"QANDA"}]}