{"Lê Ngọc Trinh":[{"snippet":"hoá\u201D. VietNamNet. ngày 12 tháng 5 năm 2021. Ngọc <span class=\"searchmatch\">Trinh<\/span> trên Facebook Ngọc <span class=\"searchmatch\">Trinh<\/span> trên Instagram <span class=\"searchmatch\">Ngoc<\/span> <span class=\"searchmatch\">Trinh<\/span> trên IMDb Kênh Ngọc <span class=\"searchmatch\">Trinh<\/span> Official trên YouTube","pageid":11934263,"title":"Ngọc Trinh (người mẫu)"},{"snippet":"Châu <span class=\"searchmatch\">Trinh<\/span>\u201D. Huyện Ủy Dân Tiên. 30 tháng 5 năm 2017. Bản gốc lưu trữ ngày 26 tháng 9 năm 2020. Truy cập ngày 30 tháng 5 năm 2020. ^ Phan, <span class=\"searchmatch\">Ngoc<\/span> Lien; <span class=\"searchmatch\">Le<\/span>, Van","pageid":368913,"title":"Bút hiệu của Hồ Chí Minh"},{"snippet":"in Vietnam Lưu trữ 2017-08-10 tại Wayback Machine Ha Viet Cuong, <span class=\"searchmatch\">Le<\/span> Van Hai, Tran <span class=\"searchmatch\">Ngoc<\/span> Tiep and Ngo Bich Hao. ISSAAS Journal Volume 17 Number 2 (Dec. 2011)","pageid":80,"title":"Hà Nội"},{"snippet":"html. |title= trống hay bị thiếu (trợ giúp) ^ https:\/\/news.zing.vn\/ho-<span class=\"searchmatch\">ngoc<\/span>-ha-am-giai-album-vang-2008-post45957.html. |title= trống hay bị thiếu (trợ","pageid":55183,"title":"Đan Trường"},{"snippet":"Conservation International, 5: 129- 135. <span class=\"searchmatch\">Le<\/span> Xuan Canh, Truong Van La, Dang Thi Dap, Ho Thu Cuc, Ngo Anh Dao, Nguyen <span class=\"searchmatch\">Ngoc<\/span> Chinh, Vu Van Dung, Pham Nhat, Nguyen","pageid":52223,"title":"Vườn quốc gia Phong Nha \u2013 Kẻ Bàng"},{"snippet":"tại Trung tâm lưu trữ quốc gia II ^ Con số khác là khoảng 1.2 triệu. Hoang <span class=\"searchmatch\">Ngoc<\/span> Lung, The General Offensives McLean VA: General Research Corporation, 1978","pageid":14210,"title":"Sự kiện Tết Mậu Thân"},{"snippet":"2021. ^ https:\/\/saostar.vn\/dien-anh\/de-cu-ngoi-sao-xanh-2020-ninh-duong-lan-<span class=\"searchmatch\">ngoc<\/span>-canh-tranh-chipu-20201208155124557.html (bằng Tiếng Việt). Truy cập ngày","pageid":3373548,"title":"Ái Phương"},{"snippet":"hipotezy, arhivnye dokumenty [Stalin, Ho Chi Minh, and the &quot;affair&quot; of Tran <span class=\"searchmatch\">Ngoc<\/span> Danh: Facts, hypothesis, archival documents]. Kursk, Russia: Kursk State","pageid":115693,"title":"Những mẩu chuyện về đời hoạt động của Hồ Chủ tịch"},{"snippet":"7 tháng 9 năm 2020. ^ Geissmann, T.; La Quang Trung; <span class=\"searchmatch\">Trinh<\/span> Dinh Hoang; Vu Dinh Thong; Dang <span class=\"searchmatch\">Ngoc<\/span> Can &amp; Pham Duc Tien, 2003: Rarest ape species rediscovered","pageid":512953,"title":"Vượn mào đen phương Đông"},{"snippet":"Ả Chạ hay Lê Ngọc <span class=\"searchmatch\">Trinh<\/span> (20 - 43) là một nữ tướng thời Hai Bà Trưng trong lịch sử Việt Nam. Lê Ngọc <span class=\"searchmatch\">Trinh<\/span> tên là Ả Nương hay Ả Chạ, có cha là ông Lê Hoàn","pageid":3203562,"title":"Lê Ngọc Trinh"}]}