{"Marcianus":[{"snippet":"<span class=\"searchmatch\">Marcianus<\/span> (tiếng Latinh: Flavius <span class=\"searchmatch\">Marcianus<\/span> Augustus; 392 \u2013 457) là Hoàng đế Đông La Mã từ năm 450 đến 457. Triều đại của ông đã đánh dấu sự phục hồi của","pageid":1750318,"title":"Marcianus"},{"snippet":"Thamnophis <span class=\"searchmatch\">marcianus<\/span> là một loài rắn trong họ Rắn nước. Loài này được Baird &amp; Girard mô tả khoa học đầu tiên năm 1853. ^ Chaves, G., Lamar, W., Porras","pageid":1767669,"title":"Thamnophis marcianus"},{"snippet":"khuynh đảo triều chính dưới thời các Hoàng đế Đông La Mã là Theodosius II, <span class=\"searchmatch\">Marcianus<\/span> và Leo I trong nửa thế kỷ, từ những năm 420 đến khi ông mất vào năm 471","pageid":2190419,"title":"Aspar"},{"snippet":"Rex (&quot;Vua&quot;) cho riêng mình. <span class=\"searchmatch\">Marcianus<\/span> là con của Hoàng đế Tây La Mã Anthemius (467\u2013472) và là cháu của Hoàng đế <span class=\"searchmatch\">Marcianus<\/span> (450\u2013457). Ông kết hôn với chị","pageid":1762948,"title":"Zeno (hoàng đế)"},{"snippet":"do Cyril of Scythopolis viết trong thế kỷ thứ 5) nói về việc Hoàng đế <span class=\"searchmatch\">Marcianus<\/span> và vợ ông, bà Pulcheria, đã hỏi Juvenal - thượng phụ Chính thống giáo","pageid":2457605,"title":"Mộ Đức Trinh nữ Maria"},{"snippet":"mangaka người Nhật Bản 98 \u2013 Nerva, hoàng đế của Đế quốc La Mã (s. 35) 457 \u2013 <span class=\"searchmatch\">Marcianus<\/span>, hoàng đế của Đế quốc Đông La Mã (s. 392) 661 \u2013 Ali bin Abu Talib, Khalip","pageid":20112,"title":"27 tháng 1"},{"snippet":"tháng 7 năm 450 và Pulcheria sớm kết hôn với tướng <span class=\"searchmatch\">Marcianus<\/span> vào ngày 25 tháng 11 năm 450. Sau đó <span class=\"searchmatch\">Marcianus<\/span> và Pulcheria được đám triều thần tôn là Hoàng đế","pageid":1749367,"title":"Pulcheria"},{"snippet":"(tiếm vị) Đế quốc Đông La Mã 395\u20131204 Arcadius Theodosius II Pulcheria <span class=\"searchmatch\">Marcianus<\/span> Leo I xứ Thracia Leo II Zeno (lần 1) Basiliscus cùng con trai Marcus là","pageid":103171,"title":"Augustus"},{"snippet":"phải trả các khoản cống phẩm lớn hàng năm cho thủ lĩnh Attila. Hoàng đế <span class=\"searchmatch\">Marcianus<\/span> sau đó đã từ chối các khoản tiền cống tốm kém nhưng lúc náy Attila đã","pageid":61402,"title":"Đế quốc Đông La Mã"},{"snippet":"(tiếm vị) Đế quốc Đông La Mã 395\u20131204 Arcadius Theodosius II Pulcheria <span class=\"searchmatch\">Marcianus<\/span> Leo I xứ Thracia Leo II Zeno (lần 1) Basiliscus cùng con trai Marcus là","pageid":131384,"title":"Constantinus Đại đế"}]}