{"Takeda Yoshinobu":[{"snippet":"<span class=\"searchmatch\">Takeda<\/span> <span class=\"searchmatch\">Yoshinobu<\/span> (武田 義信, <span class=\"searchmatch\">Takeda<\/span> <span class=\"searchmatch\">Yoshinobu<\/span>?, Vũ Điền Nghĩa Tín) (1538 - 19\/11\/1567) là một daimyo thời kỳ Sengoku, ông là con trai cả của <span class=\"searchmatch\">Takeda<\/span> Shingen","pageid":172577,"title":"Takeda Yoshinobu"},{"snippet":"(館林徳川家) - hậu duệ của Tokugawa Tsunayoshi. Nhà Tokugawa <span class=\"searchmatch\">Yoshinobu<\/span> (徳川慶喜家) - hậu duệ của Tokugawa <span class=\"searchmatch\">Yoshinobu<\/span>. Gosanke (御三家) Nhà Tokugawa của Kishū (紀州徳川家) - cũng","pageid":3520806,"title":"Gia tộc Nhật Bản"},{"snippet":"đã được Natsume <span class=\"searchmatch\">Yoshinobu<\/span> thực hiện thành công với kết quả là tính mạng của Ieyasu được bảo toàn. Tuy vậy, <span class=\"searchmatch\">Yoshinobu<\/span> đã bị quân <span class=\"searchmatch\">Takeda<\/span> giết chết khi ông","pageid":3170012,"title":"Trận Mikatagahara"},{"snippet":"gia tộc <span class=\"searchmatch\">Takeda<\/span> kết thúc năm 1582 khi liên quân Oda-Tokugawa tấn công và chiếm được tỉnh Kai. <span class=\"searchmatch\">Takeda<\/span> Katsuyori, cũng như người con trưởng <span class=\"searchmatch\">Takeda<\/span> Nobukatsu","pageid":116350,"title":"Tokugawa Ieyasu"},{"snippet":"Nobushige và <span class=\"searchmatch\">Yoshinobu<\/span>. Điều này đã khiến cho Yoshikiyo đưa lá thư tới Uesugi Kenshin và đã bắt đầu trận chiến huyền thoại giữa <span class=\"searchmatch\">Takeda<\/span> và Kenshin ở cánh","pageid":166348,"title":"Takeda Nobushige"},{"snippet":"tháng 9 năm 1888 \u2013 8 tháng 3 năm 1940), kết hôn với Vương tước <span class=\"searchmatch\">Takeda<\/span> Tsunehisa (<span class=\"searchmatch\">Takeda<\/span>-no-miya Tsunehisa ō, 22 tháng 9 năm 1882 \u2013 23 tháng 4 năm 1919)","pageid":131065,"title":"Thiên hoàng Minh Trị"},{"snippet":"của Shinsengumi). Tháng 10 năm Keiō thứ 3 (1867), tướng quân Tokugawa <span class=\"searchmatch\">Yoshinobu<\/span> thực hiện Đại Chính Phụng Hoàn. Tuy nhiên, Shinsengumi vẫn trung thành","pageid":237330,"title":"Shinsengumi"},{"snippet":"tài năng của Shingen là <span class=\"searchmatch\">Takeda<\/span> Nobushige và người chú là Morozumi Masakiyo đã hi sinh ngay trong trận chiến.<span class=\"searchmatch\">Takeda<\/span> <span class=\"searchmatch\">Yoshinobu<\/span> người thừa kế của Shingen","pageid":44890,"title":"Yamamoto Kansuke"},{"snippet":"nhiệm Thủ tướng. Minh Trị Duy Tân năm 1868 khiến Tướng quân Tokugawa <span class=\"searchmatch\">Yoshinobu<\/span> từ chức, đồng ý &quot;làm công cụ thi hành&quot; mệnh lệnh Thiên hoàng. Sự kiện","pageid":3521061,"title":"Chính phủ Nhật Bản"},{"snippet":"tỉnh và bị cảnh sát bắt giữ. <span class=\"searchmatch\">Takeda<\/span> Kanryū hơi dựa trên đội trưởng thứ năm của Shinsengumi là <span class=\"searchmatch\">Takeda<\/span> Kanryusai. Vì <span class=\"searchmatch\">Takeda<\/span> Kanrūysai bị đồn là người đồng","pageid":237662,"title":"Danh sách nhân vật trong Rurouni Kenshin"}]}